shinny_parsing/__init__.py
shinny_parsing/parse_settlement_infos.py
shinny_parsing/parse_to_dataframe.py
shinny_parsing-0.0.4.dist-info/METADATA
shinny_parsing-0.0.4.dist-info/WHEEL
shinny_parsing-0.0.4.dist-info/top_level.txt
shinny_parsing-0.0.4.dist-info/RECORD
