Metadata-Version: 2.1
Name: shinny-parsing
Version: 0.0.4
Summary: parse settlement file
Home-page: https://www.shinnytech.com/
Author: mayanqiong
Author-email: mayanqiong@shinnytech.com
Classifier: Programming Language :: Python :: 3
Classifier: License :: OSI Approved :: Apache Software License
Classifier: Operating System :: OS Independent
Requires-Python: >=3.6
Requires-Dist: pandas
